setup.py
dataRX/__init__.py
dataRX/processor.py
dataRX.egg-info/PKG-INFO
dataRX.egg-info/SOURCES.txt
dataRX.egg-info/dependency_links.txt
dataRX.egg-info/not-zip-safe
dataRX.egg-info/requires.txt
dataRX.egg-info/top_level.txt