Metadata-Version: 1.0
Name: dataRX
Version: 2.0
Summary: Extension used to import, read, and give preliminary descriptive statistics of data files.
Home-page: https://github.com/ralston3/dataRX/
Author: Rashad Alston
Author-email: ralston@yahoo-inc.com
License: BDS 3 Clause
Platform: any
